ansible_builder/__init__.py
ansible_builder/__main__.py
ansible_builder/cli.py
ansible_builder/colors.py
ansible_builder/constants.py
ansible_builder/containerfile.py
ansible_builder/ee_schema.py
ansible_builder/exceptions.py
ansible_builder/main.py
ansible_builder/policies.py
ansible_builder/user_definition.py
ansible_builder/utils.py
ansible_builder/_target_scripts/__init__.py
ansible_builder/_target_scripts/assemble
ansible_builder/_target_scripts/check_ansible
ansible_builder/_target_scripts/check_galaxy
ansible_builder/_target_scripts/entrypoint
ansible_builder/_target_scripts/install-from-bindep
ansible_builder/_target_scripts/introspect.py
ansible_builder-3.0.1.dist-info/LICENSE.md
ansible_builder-3.0.1.dist-info/METADATA
ansible_builder-3.0.1.dist-info/WHEEL
ansible_builder-3.0.1.dist-info/entry_points.txt
ansible_builder-3.0.1.dist-info/top_level.txt
ansible_builder-3.0.1.dist-info/RECORD
