Metadata-Version: 2.1
Name: ansible-builder
Version: 3.0.1
Summary: "A tool for building Ansible Execution Environments"
Home-page: https://ansible-builder.readthedocs.io
Author: Ansible, Inc.
Author-email: info@ansible.com
License: Apache Software License, Version 2.0
Classifier: Development Status :: 5 - Production/Stable
Classifier: Environment :: Console
Classifier: Intended Audience :: Developers
Classifier: Intended Audience :: Information Technology
Classifier: Intended Audience :: System Administrators
Classifier: License :: OSI Approved :: Apache Software License
Classifier: Natural Language :: English
Classifier: Operating System :: POSIX
Classifier: Programming Language :: Python :: 3.9
Classifier: Programming Language :: Python :: 3.10
Classifier: Programming Language :: Python :: 3.11
Classifier: Programming Language :: Python :: 3 :: Only
Classifier: Topic :: Software Development :: Build Tools
Classifier: Topic :: System :: Systems Administration
Classifier: Topic :: Utilities
Requires-Python: >=3.9
License-File: LICENSE.md
Requires-Dist: PyYAML
Requires-Dist: requirements-parser
Requires-Dist: bindep
Requires-Dist: jsonschema
